rfit/__init__.py
rfit/api.py
rfit/learn/__init__.py
rfit/learn/boundary_plots.py
rfit/learn/grads.py
rfit/learn/helper.py
rfit/learn/tf_utils.py
rfit-0.7.20241220.dist-info/LICENSE
rfit-0.7.20241220.dist-info/METADATA
rfit-0.7.20241220.dist-info/WHEEL
rfit-0.7.20241220.dist-info/top_level.txt
rfit-0.7.20241220.dist-info/RECORD
