Metadata-Version: 2.1
Name: rfit
Version: 0.7.20241220
Summary: University of Chicago Data Science Institute python class helper functions
Home-page: https://github.com/physicsland/rfitapi
Author: Edwin Lo
Author-email: elo@regression.fit
Project-URL: Bug Tracker, https://github.com/physicsland/rfitapi/issues
Classifier: Programming Language :: Python :: 3
Classifier: License :: OSI Approved :: MIT License
Classifier: Operating System :: OS Independent
Requires-Python: >=3.6
License-File: LICENSE
Requires-Dist: numpy
Requires-Dist: matplotlib
Requires-Dist: pandas
Requires-Dist: requests
Requires-Dist: mysql.connector
Requires-Dist: scikit-learn
Requires-Dist: tensorflow
